[{"source": "Claudia Arozqueta", "target": "searchlights"}, {"source": "Claudia Arozqueta", "target": "artificial light"}, {"source": "Claudia Arozqueta", "target": "surveillance"}, {"source": "Claudia Arozqueta", "target": "installation art"}, {"source": "Claudia Arozqueta", "target": "memorial art"}, {"source": "Claudia Arozqueta", "target": "war"}, {"source": "Claudia Arozqueta", "target": "spectacle"}, {"source": "Claudia Arozqueta", "target": "media art history."}, {"source": "Donna Szoke", "target": "invisible animals"}, {"source": "Donna Szoke", "target": "non-human animals"}, {"source": "Donna Szoke", "target": "hallucinations"}, {"source": "Donna Szoke", "target": "fabulations"}, {"source": "Donna Szoke", "target": "ghosts"}, {"source": "Donna Szoke", "target": "media art"}, {"source": "Donna Szoke", "target": "video art"}, {"source": "Donna Szoke", "target": "geolocation"}, {"source": "Donna Szoke", "target": "immanence"}, {"source": "Donna Szoke", "target": "artist-research."}, {"source": "Sihwa Park", "target": "self-representation"}, {"source": "Sihwa Park", "target": "quantified self"}, {"source": "Sihwa Park", "target": "mobile phone use behavior"}, {"source": "Sihwa Park", "target": "data art"}, {"source": "Sihwa Park", "target": "multimodal data representation"}, {"source": "Sihwa Park", "target": "visualization"}, {"source": "Sihwa Park", "target": "sonification"}, {"source": "Sihwa Park", "target": "indexicality"}, {"source": "Sihwa Park", "target": "heatmap"}, {"source": "Sihwa Park", "target": "websocket"}, {"source": "Sihwa Park", "target": "webaudio "}, {"source": "Zane Cerpina", "target": "ecological surveillance"}, {"source": "Zane Cerpina", "target": "biosensing technology"}, {"source": "Zane Cerpina", "target": "plant based intelligence"}, {"source": "Zane Cerpina", "target": "environmental adaptation"}, {"source": "Zane Cerpina", "target": "amazon rainforest"}, {"source": "Zane Cerpina", "target": "speculative design."}, {"source": "Jongcheon Shin, Siwon Lee, Suk Chon, Keyan Jiang & Joonsung Yoon", "target": "bio-art"}, {"source": "Jongcheon Shin, Siwon Lee, Suk Chon, Keyan Jiang & Joonsung Yoon", "target": "schr\u00f6dinger\u2019s hypothesis of life"}, {"source": "Jongcheon Shin, Siwon Lee, Suk Chon, Keyan Jiang & Joonsung Yoon", "target": "merleau-ponty\u2019s painting theory"}, {"source": "Jongcheon Shin, Siwon Lee, Suk Chon, Keyan Jiang & Joonsung Yoon", "target": "genesis of things"}, {"source": "Jongcheon Shin, Siwon Lee, Suk Chon, Keyan Jiang & Joonsung Yoon", "target": "communion"}, {"source": "Jongcheon Shin, Siwon Lee, Suk Chon, Keyan Jiang & Joonsung Yoon", "target": "painting system"}, {"source": "Jongcheon Shin, Siwon Lee, Suk Chon, Keyan Jiang & Joonsung Yoon", "target": "bio-art system"}, {"source": "Anne Nigten & Annemarie Piscaer", "target": "art education"}, {"source": "Anne Nigten & Annemarie Piscaer", "target": "hybrid learning"}, {"source": "Anne Nigten & Annemarie Piscaer", "target": "transdisciplinary collabora- tion"}, {"source": "Anne Nigten & Annemarie Piscaer", "target": "life long learning"}, {"source": "Anne Nigten & Annemarie Piscaer", "target": "participatory design"}, {"source": "Anne Nigten & Annemarie Piscaer", "target": "peer-learning"}, {"source": "Anne Nigten & Annemarie Piscaer", "target": "creativity"}, {"source": "Anne Nigten & Annemarie Piscaer", "target": "improvisation"}, {"source": "Anne Nigten & Annemarie Piscaer", "target": "situated design"}, {"source": "Anne Nigten & Annemarie Piscaer", "target": "transition design"}, {"source": "Anne Nigten & Annemarie Piscaer", "target": "amateurs"}, {"source": "Anne Nigten & Annemarie Piscaer", "target": "pro-am"}, {"source": "Anatol Bologan, Dr. Jinsil Seo, Joseph Orr & Vidya Sridhar", "target": "art"}, {"source": "Anatol Bologan, Dr. Jinsil Seo, Joseph Orr & Vidya Sridhar", "target": "interactive art"}, {"source": "Anatol Bologan, Dr. Jinsil Seo, Joseph Orr & Vidya Sridhar", "target": "installation"}, {"source": "Anatol Bologan, Dr. Jinsil Seo, Joseph Orr & Vidya Sridhar", "target": "human consciousness"}, {"source": "Anatol Bologan, Dr. Jinsil Seo, Joseph Orr & Vidya Sridhar", "target": "hu- man cognition"}, {"source": "Anatol Bologan, Dr. Jinsil Seo, Joseph Orr & Vidya Sridhar", "target": "medical imaging"}, {"source": "Anatol Bologan, Dr. Jinsil Seo, Joseph Orr & Vidya Sridhar", "target": "fmri"}, {"source": "Anatol Bologan, Dr. Jinsil Seo, Joseph Orr & Vidya Sridhar", "target": "brain activity."}, {"source": "Jeehyun Yang, Jaesik Jeong & Jacky Baltes", "target": "robot performance art"}, {"source": "Jeehyun Yang, Jaesik Jeong & Jacky Baltes", "target": "humanoid robot"}, {"source": "Jeehyun Yang, Jaesik Jeong & Jacky Baltes", "target": "robot magic show"}, {"source": "Jeehyun Yang, Jaesik Jeong & Jacky Baltes", "target": "robot personality"}, {"source": "Jeehyun Yang, Jaesik Jeong & Jacky Baltes", "target": "verbal & non-verbal communication"}, {"source": "Jeehyun Yang, Jaesik Jeong & Jacky Baltes", "target": "human robot interaction"}, {"source": "Jeehyun Yang, Jaesik Jeong & Jacky Baltes", "target": "roulette wheel selection"}, {"source": "Michel van Dartel & Alwin de Rooij", "target": "sensory augmentation; public space; artistic research; interface design; cognitive science; applications"}, {"source": "Georgia Smithson", "target": "new media art"}, {"source": "Georgia Smithson", "target": "collecting"}, {"source": "Georgia Smithson", "target": "documentation"}, {"source": "Georgia Smithson", "target": "distribution"}, {"source": "Georgia Smithson", "target": "access"}, {"source": "Georgia Smithson", "target": "collaboration"}, {"source": "Georgia Smithson", "target": "experimentation"}, {"source": "Georgia Smithson", "target": "innovation"}, {"source": "Georgia Smithson", "target": "networks"}, {"source": "Varvara Guljajeva", "target": "interactive art"}, {"source": "Varvara Guljajeva", "target": "post-participation"}, {"source": "Varvara Guljajeva", "target": "surveillance"}, {"source": "Varvara Guljajeva", "target": "interactive systems"}, {"source": "Varvara Guljajeva", "target": "hybrid art"}, {"source": "Varvara Guljajeva", "target": "practice-based research"}, {"source": "Varvara Guljajeva", "target": "post-digital."}, {"source": "Steven Devleminck, Boris Debackere & Toon Van Waterschoot", "target": "liquid"}, {"source": "Steven Devleminck, Boris Debackere & Toon Van Waterschoot", "target": "cartography"}, {"source": "Steven Devleminck, Boris Debackere & Toon Van Waterschoot", "target": "multi-viewpoint"}, {"source": "Steven Devleminck, Boris Debackere & Toon Van Waterschoot", "target": "sound"}, {"source": "Steven Devleminck, Boris Debackere & Toon Van Waterschoot", "target": "localization and auralization"}, {"source": "Steven Devleminck, Boris Debackere & Toon Van Waterschoot", "target": "technology"}, {"source": "Steven Devleminck, Boris Debackere & Toon Van Waterschoot", "target": "multi-sensory integration"}, {"source": "Jiabao Li, Honghao Deng & Panagiotis Michalatos", "target": "wearable"}, {"source": "Jiabao Li, Honghao Deng & Panagiotis Michalatos", "target": " speculative design"}, {"source": "Jiabao Li, Honghao Deng & Panagiotis Michalatos", "target": "augmented reality"}, {"source": "Jiabao Li, Honghao Deng & Panagiotis Michalatos", "target": "vision,tactile art,soft robotics"}, {"source": "Marinos Koutsomichalis", "target": "physicalization"}, {"source": "Marinos Koutsomichalis", "target": "post-digital"}, {"source": "Marinos Koutsomichalis", "target": "3d printing"}, {"source": "Marinos Koutsomichalis", "target": "solid modeling"}, {"source": "Marinos Koutsomichalis", "target": "digital fabrication"}, {"source": "Marinos Koutsomichalis", "target": "natural language understanding"}, {"source": "Marinos Koutsomichalis", "target": "3d data."}, {"source": "Sojung Bahng, Toby Gifford & Jon McCormack", "target": "virtual reality"}, {"source": "Sojung Bahng, Toby Gifford & Jon McCormack", "target": "cinematic vr"}, {"source": "Sojung Bahng, Toby Gifford & Jon McCormack", "target": "empathy"}, {"source": "Sojung Bahng, Toby Gifford & Jon McCormack", "target": "reflexivity"}, {"source": "Sojung Bahng, Toby Gifford & Jon McCormack", "target": "alienation"}, {"source": "Sojung Bahng, Toby Gifford & Jon McCormack", "target": "immersive storytelling."}, {"source": "Hyun Jean Lee, Wonjean Lee, Hyungsin Kim & Jeong Han Kim", "target": "ten diagrams on sage learning"}, {"source": "Hyun Jean Lee, Wonjean Lee, Hyungsin Kim & Jeong Han Kim", "target": "virtual reality"}, {"source": "Hyun Jean Lee, Wonjean Lee, Hyungsin Kim & Jeong Han Kim", "target": "philo- sophical space-time"}, {"source": "Hyun Jean Lee, Wonjean Lee, Hyungsin Kim & Jeong Han Kim", "target": "experience design"}, {"source": "Hyun Jean Lee, Wonjean Lee, Hyungsin Kim & Jeong Han Kim", "target": "mindfulness"}, {"source": "Benjamin Horn", "target": "uncertainty"}, {"source": "Benjamin Horn", "target": "game studies"}, {"source": "Benjamin Horn", "target": "hermeneutics"}, {"source": "Benjamin Horn", "target": "ludonarratives"}, {"source": "Benjamin Horn", "target": "hollow knight"}, {"source": "Benjamin Horn", "target": "ori and the blind forest"}, {"source": "Benjamin Horn", "target": "comparative game analysis"}, {"source": "Intae Hwang & Alenda Y. Chang", "target": "jeong seon"}, {"source": "Intae Hwang & Alenda Y. Chang", "target": "korean landscape painting"}, {"source": "Intae Hwang & Alenda Y. Chang", "target": "virtual reality"}, {"source": "Intae Hwang & Alenda Y. Chang", "target": "immersive virtual environments"}, {"source": "Intae Hwang & Alenda Y. Chang", "target": "anamorphosis"}, {"source": "Intae Hwang & Alenda Y. Chang", "target": "fisheye view"}, {"source": "Intae Hwang & Alenda Y. Chang", "target": "panorama effect."}, {"source": "Bert Vandenberghe, Kathrin Gerling, Luc Geurts, Vero Vanden Abeele & Steven Devleminck", "target": "human-computer interaction"}, {"source": "Bert Vandenberghe, Kathrin Gerling, Luc Geurts, Vero Vanden Abeele & Steven Devleminck", "target": "lived-in world"}, {"source": "Bert Vandenberghe, Kathrin Gerling, Luc Geurts, Vero Vanden Abeele & Steven Devleminck", "target": "methodology"}, {"source": "Bert Vandenberghe, Kathrin Gerling, Luc Geurts, Vero Vanden Abeele & Steven Devleminck", "target": "skweezee"}, {"source": "Bert Vandenberghe, Kathrin Gerling, Luc Geurts, Vero Vanden Abeele & Steven Devleminck", "target": "interactive technology"}, {"source": "Bert Vandenberghe, Kathrin Gerling, Luc Geurts, Vero Vanden Abeele & Steven Devleminck", "target": "toolkit."}, {"source": "Ardavan Bidgoli, Eunsu Kang & Daniel Cardoso Llach", "target": "artificial intelligence"}, {"source": "Ardavan Bidgoli, Eunsu Kang & Daniel Cardoso Llach", "target": "machine learning"}, {"source": "Ardavan Bidgoli, Eunsu Kang & Daniel Cardoso Llach", "target": "co-creation"}, {"source": "Ardavan Bidgoli, Eunsu Kang & Daniel Cardoso Llach", "target": "collaboration"}, {"source": "Ardavan Bidgoli, Eunsu Kang & Daniel Cardoso Llach", "target": "human-machine interaction"}, {"source": "Ardavan Bidgoli, Eunsu Kang & Daniel Cardoso Llach", "target": "computational creativity"}, {"source": "Ardavan Bidgoli, Eunsu Kang & Daniel Cardoso Llach", "target": "art"}, {"source": "Ardavan Bidgoli, Eunsu Kang & Daniel Cardoso Llach", "target": "design"}, {"source": "Ardavan Bidgoli, Eunsu Kang & Daniel Cardoso Llach", "target": "machinic surrogacy"}, {"source": "Ardavan Bidgoli, Eunsu Kang & Daniel Cardoso Llach", "target": "ai-enabled tools"}, {"source": "Minso Kim", "target": "virtual images"}, {"source": "Minso Kim", "target": "frame"}, {"source": "Minso Kim", "target": "aura"}, {"source": "Minso Kim", "target": "screen-without-sound"}, {"source": "Minso Kim", "target": "digital creative work"}, {"source": "Minso Kim", "target": "digital performance"}, {"source": "Minso Kim", "target": "telematic dreaming"}, {"source": "Tadeus Mucelli", "target": "art"}, {"source": "Tadeus Mucelli", "target": "technology"}, {"source": "Tadeus Mucelli", "target": "philosophy"}, {"source": "Tadeus Mucelli", "target": "biotechnology"}, {"source": "Tadeus Mucelli", "target": "curatorship"}, {"source": "Tadeus Mucelli", "target": "digital art biennial"}, {"source": "Semi Ryu, Danielle Noreika, Malisa Dang & Egidio Del Fabbro", "target": "avatar"}, {"source": "Semi Ryu, Danielle Noreika, Malisa Dang & Egidio Del Fabbro", "target": "storytelling"}, {"source": "Semi Ryu, Danielle Noreika, Malisa Dang & Egidio Del Fabbro", "target": "digital immortality"}, {"source": "Semi Ryu, Danielle Noreika, Malisa Dang & Egidio Del Fabbro", "target": "life-review"}, {"source": "Semi Ryu, Danielle Noreika, Malisa Dang & Egidio Del Fabbro", "target": "virtual reality"}, {"source": "Semi Ryu, Danielle Noreika, Malisa Dang & Egidio Del Fabbro", "target": "mixed reality"}, {"source": "Semi Ryu, Danielle Noreika, Malisa Dang & Egidio Del Fabbro", "target": "palliative care"}, {"source": "Semi Ryu, Danielle Noreika, Malisa Dang & Egidio Del Fabbro", "target": "thana technology"}, {"source": "Semi Ryu, Danielle Noreika, Malisa Dang & Egidio Del Fabbro", "target": "embodiment"}, {"source": "Semi Ryu, Danielle Noreika, Malisa Dang & Egidio Del Fabbro", "target": "korean shamanism "}, {"source": "Aleksandra Dulic & Miles Thorogood", "target": "generative art"}, {"source": "Aleksandra Dulic & Miles Thorogood", "target": "sustainability"}, {"source": "Aleksandra Dulic & Miles Thorogood", "target": "dynamic composition"}, {"source": "Aleksandra Dulic & Miles Thorogood", "target": "resilient communities"}, {"source": "Yingdao Jiang, Li Yang, Yingquan Wang & Joonsung Yoon", "target": "chinese intangible cultural heritage"}, {"source": "Yingdao Jiang, Li Yang, Yingquan Wang & Joonsung Yoon", "target": "mobile application platform design"}, {"source": "Yingdao Jiang, Li Yang, Yingquan Wang & Joonsung Yoon", "target": "chinese traditional shadow art"}, {"source": "Claudia Costa Pederson", "target": "ecology"}, {"source": "Claudia Costa Pederson", "target": "art"}, {"source": "Claudia Costa Pederson", "target": "technology"}, {"source": "Claudia Costa Pederson", "target": "heterochronocity"}, {"source": "Claudia Costa Pederson", "target": "progressivism"}, {"source": "Claudia Costa Pederson", "target": "drainage"}, {"source": "Claudia Costa Pederson", "target": "enlightenment"}, {"source": "Claudia Costa Pederson", "target": "latin america"}, {"source": "Claudia Costa Pederson", "target": "colonization"}, {"source": "Claudia Costa Pederson", "target": "renaissance"}, {"source": "Claudia Costa Pederson", "target": "venice"}, {"source": "Claudia Costa Pederson", "target": "biennale"}, {"source": "Claudia Costa Pederson", "target": "mexico city."}, {"source": "Jinsil Hwaryoung Seo, Eman Al-Zubeidi, Courtney Michalsky, Stephanie Sykora & Lauren Toler", "target": "interactive art"}, {"source": "Jinsil Hwaryoung Seo, Eman Al-Zubeidi, Courtney Michalsky, Stephanie Sykora & Lauren Toler", "target": "public art"}, {"source": "Jinsil Hwaryoung Seo, Eman Al-Zubeidi, Courtney Michalsky, Stephanie Sykora & Lauren Toler", "target": "public awareness"}, {"source": "Jinsil Hwaryoung Seo, Eman Al-Zubeidi, Courtney Michalsky, Stephanie Sykora & Lauren Toler", "target": "poverty"}, {"source": "Jinsil Hwaryoung Seo, Eman Al-Zubeidi, Courtney Michalsky, Stephanie Sykora & Lauren Toler", "target": "community"}, {"source": "Maria Lantin, Alexandra Hass, Simon Lysander Overstall", "target": "living"}, {"source": "Maria Lantin, Alexandra Hass, Simon Lysander Overstall", "target": "dying"}, {"source": "Maria Lantin, Alexandra Hass, Simon Lysander Overstall", "target": "organic matter"}, {"source": "Maria Lantin, Alexandra Hass, Simon Lysander Overstall", "target": "time"}, {"source": "Maria Lantin, Alexandra Hass, Simon Lysander Overstall", "target": "space"}, {"source": "Maria Lantin, Alexandra Hass, Simon Lysander Overstall", "target": "sampling"}, {"source": "Maria Lantin, Alexandra Hass, Simon Lysander Overstall", "target": "scanner"}, {"source": "Maria Lantin, Alexandra Hass, Simon Lysander Overstall", "target": "procedural video"}, {"source": "Maria Lantin, Alexandra Hass, Simon Lysander Overstall", "target": "procedural sound"}, {"source": "Maria Lantin, Alexandra Hass, Simon Lysander Overstall", "target": "ambient"}, {"source": "Honghao Deng, Jiabao Li, Allen Sayegh", "target": "affective computing"}, {"source": "Honghao Deng, Jiabao Li, Allen Sayegh", "target": "uav"}, {"source": "Honghao Deng, Jiabao Li, Allen Sayegh", "target": "urban lighting"}, {"source": "Honghao Deng, Jiabao Li, Allen Sayegh", "target": "autonomous aircraft"}, {"source": "Honghao Deng, Jiabao Li, Allen Sayegh", "target": "interactive"}, {"source": "Honghao Deng, Jiabao Li, Allen Sayegh", "target": "play"}, {"source": "Songwei Ge, Austin Dill, Eunsu Kang, Chun-Liang Li, Lingyao Zhang Manzil Zaheer & Barnabas Poczos", "target": "partitioned deepdream"}, {"source": "Songwei Ge, Austin Dill, Eunsu Kang, Chun-Liang Li, Lingyao Zhang Manzil Zaheer & Barnabas Poczos", "target": "amalgamated deepdream"}, {"source": "Songwei Ge, Austin Dill, Eunsu Kang, Chun-Liang Li, Lingyao Zhang Manzil Zaheer & Barnabas Poczos", "target": "3d"}, {"source": "Songwei Ge, Austin Dill, Eunsu Kang, Chun-Liang Li, Lingyao Zhang Manzil Zaheer & Barnabas Poczos", "target": "point cloud"}, {"source": "Songwei Ge, Austin Dill, Eunsu Kang, Chun-Liang Li, Lingyao Zhang Manzil Zaheer & Barnabas Poczos", "target": "sculpture"}, {"source": "Songwei Ge, Austin Dill, Eunsu Kang, Chun-Liang Li, Lingyao Zhang Manzil Zaheer & Barnabas Poczos", "target": "art"}, {"source": "Songwei Ge, Austin Dill, Eunsu Kang, Chun-Liang Li, Lingyao Zhang Manzil Zaheer & Barnabas Poczos", "target": "interactive installation"}, {"source": "Songwei Ge, Austin Dill, Eunsu Kang, Chun-Liang Li, Lingyao Zhang Manzil Zaheer & Barnabas Poczos", "target": "creative ai"}, {"source": "Songwei Ge, Austin Dill, Eunsu Kang, Chun-Liang Li, Lingyao Zhang Manzil Zaheer & Barnabas Poczos", "target": "machine learning"}, {"source": "Sey Min & Jihye Lee", "target": "artificial intelligence"}, {"source": "Sey Min & Jihye Lee", "target": "machine learning"}, {"source": "Sey Min & Jihye Lee", "target": "ai creativity"}, {"source": "Sey Min & Jihye Lee", "target": "visualization"}, {"source": "Sey Min & Jihye Lee", "target": "sound visualization"}, {"source": "Clarissa Ribeiro", "target": "data visualization"}, {"source": "Clarissa Ribeiro", "target": "hashtag wars"}, {"source": "Clarissa Ribeiro", "target": "twitter"}, {"source": "Clarissa Ribeiro", "target": "brazil presidential elections"}, {"source": "Clarissa Ribeiro", "target": "social media"}, {"source": "Clarissa Ribeiro", "target": "assembly of god"}, {"source": "Clarissa Ribeiro", "target": "trolls"}, {"source": "Clarissa Ribeiro", "target": "bots"}, {"source": "Clarissa Ribeiro", "target": "political crystals"}, {"source": "Clarissa Ribeiro", "target": "silicon valley"}, {"source": "Clarissa Ribeiro", "target": "digital fabrication"}, {"source": "Clarissa Ribeiro", "target": "altered reality"}, {"source": "Clarissa Ribeiro", "target": "virtual reality"}, {"source": "Clarissa Ribeiro", "target": "digital fabrication"}, {"source": "Clarissa Ribeiro", "target": "parametric design"}, {"source": "Clarissa Ribeiro", "target": "morphogenetic design"}, {"source": "Clarissa Ribeiro", "target": "algorithmic design."}, {"source": "Jiayue Cecilia Wu & Donghao Ren", "target": "data visualization"}, {"source": "Jiayue Cecilia Wu & Donghao Ren", "target": "hashtag wars"}, {"source": "Jiayue Cecilia Wu & Donghao Ren", "target": "twitter"}, {"source": "Jiayue Cecilia Wu & Donghao Ren", "target": "brazil presidential elections"}, {"source": "Jiayue Cecilia Wu & Donghao Ren", "target": "social media"}, {"source": "Jiayue Cecilia Wu & Donghao Ren", "target": "assembly of god"}, {"source": "Jiayue Cecilia Wu & Donghao Ren", "target": "trolls"}, {"source": "Jiayue Cecilia Wu & Donghao Ren", "target": "bots"}, {"source": "Jiayue Cecilia Wu & Donghao Ren", "target": "political crystals"}, {"source": "Jiayue Cecilia Wu & Donghao Ren", "target": "silicon valley"}, {"source": "Jiayue Cecilia Wu & Donghao Ren", "target": "digital fabrication"}, {"source": "Jiayue Cecilia Wu & Donghao Ren", "target": "altered reality"}, {"source": "Jiayue Cecilia Wu & Donghao Ren", "target": "virtual reality"}, {"source": "Jiayue Cecilia Wu & Donghao Ren", "target": "digital fabrication"}, {"source": "Jiayue Cecilia Wu & Donghao Ren", "target": "parametric design"}, {"source": "Jiayue Cecilia Wu & Donghao Ren", "target": "morphogenetic design"}, {"source": "Jiayue Cecilia Wu & Donghao Ren", "target": "algorithmic design."}, {"source": "Lingdong Huang, Zheng Jiang, Syuan-Cheng Sun, Tong Bai, Eunsu Kang & Barnabas Poczos", "target": "opera"}, {"source": "Lingdong Huang, Zheng Jiang, Syuan-Cheng Sun, Tong Bai, Eunsu Kang & Barnabas Poczos", "target": "kunqu"}, {"source": "Lingdong Huang, Zheng Jiang, Syuan-Cheng Sun, Tong Bai, Eunsu Kang & Barnabas Poczos", "target": "audiovisual"}, {"source": "Lingdong Huang, Zheng Jiang, Syuan-Cheng Sun, Tong Bai, Eunsu Kang & Barnabas Poczos", "target": "machine learning"}, {"source": "Lingdong Huang, Zheng Jiang, Syuan-Cheng Sun, Tong Bai, Eunsu Kang & Barnabas Poczos", "target": "artificial intelligence"}, {"source": "Lingdong Huang, Zheng Jiang, Syuan-Cheng Sun, Tong Bai, Eunsu Kang & Barnabas Poczos", "target": "ai art"}, {"source": "Lingdong Huang, Zheng Jiang, Syuan-Cheng Sun, Tong Bai, Eunsu Kang & Barnabas Poczos", "target": "total art"}, {"source": "Lingdong Huang, Zheng Jiang, Syuan-Cheng Sun, Tong Bai, Eunsu Kang & Barnabas Poczos", "target": "gesamtkunstwerk"}, {"source": "Lingdong Huang, Zheng Jiang, Syuan-Cheng Sun, Tong Bai, Eunsu Kang & Barnabas Poczos", "target": "lstm"}, {"source": "Lingdong Huang, Zheng Jiang, Syuan-Cheng Sun, Tong Bai, Eunsu Kang & Barnabas Poczos", "target": "pix2pix"}, {"source": "Lingdong Huang, Zheng Jiang, Syuan-Cheng Sun, Tong Bai, Eunsu Kang & Barnabas Poczos", "target": "rnn"}, {"source": "Lingdong Huang, Zheng Jiang, Syuan-Cheng Sun, Tong Bai, Eunsu Kang & Barnabas Poczos", "target": "markov chain"}, {"source": "Lingdong Huang, Zheng Jiang, Syuan-Cheng Sun, Tong Bai, Eunsu Kang & Barnabas Poczos", "target": "openpose"}, {"source": "Brendan Harwood", "target": "light"}, {"source": "Brendan Harwood", "target": "sculpture"}, {"source": "Brendan Harwood", "target": "projections"}, {"source": "Brendan Harwood", "target": "lasers"}, {"source": "Brendan Harwood", "target": "volumetric light"}, {"source": "Brendan Harwood", "target": "darkness"}, {"source": "Brendan Harwood", "target": "apparatus"}, {"source": "Brendan Harwood", "target": "form."}, {"source": "Haru (Hyunkyung) Ji & Graham Wakefield", "target": "art installation"}, {"source": "Haru (Hyunkyung) Ji & Graham Wakefield", "target": "artificial life"}, {"source": "Haru (Hyunkyung) Ji & Graham Wakefield", "target": "embodiment"}, {"source": "Haru (Hyunkyung) Ji & Graham Wakefield", "target": "interactive art"}, {"source": "Haru (Hyunkyung) Ji & Graham Wakefield", "target": "mixed reality"}, {"source": "Haru (Hyunkyung) Ji & Graham Wakefield", "target": "physical computing"}, {"source": "Haru (Hyunkyung) Ji & Graham Wakefield", "target": "shadows"}, {"source": "Haru (Hyunkyung) Ji & Graham Wakefield", "target": "sitespecific"}, {"source": "Haru (Hyunkyung) Ji & Graham Wakefield", "target": "spatial sound"}, {"source": "Haru (Hyunkyung) Ji & Graham Wakefield", "target": "virtual reality"}, {"source": "Ian Willcock", "target": "collective consciousness social media"}, {"source": "Ian Willcock", "target": "augmented reality big data"}, {"source": "Ian Willcock", "target": "knowledge systems and thought"}, {"source": "Ian Willcock", "target": "generative digital art"}, {"source": "Ian Willcock", "target": "digital narratives"}, {"source": "Kyle Chung", "target": "curatorship"}, {"source": "Kyle Chung", "target": "social media"}, {"source": "Kyle Chung", "target": "generation z"}, {"source": "Kyle Chung", "target": "media art"}, {"source": "Kyle Chung", "target": "audience participation"}, {"source": "Kyle Chung", "target": "engagement"}, {"source": "Kyle Chung", "target": "museum studies"}, {"source": "Kyle Chung", "target": "arts management"}, {"source": "Kyle Chung", "target": "audience behaviour"}, {"source": "Benjamin Seide, Ross Williams & Elke Reinhuber", "target": "virtual reality experience"}, {"source": "Benjamin Seide, Ross Williams & Elke Reinhuber", "target": "virtual heritage"}, {"source": "Benjamin Seide, Ross Williams & Elke Reinhuber", "target": "photogrammetry"}, {"source": "Benjamin Seide, Ross Williams & Elke Reinhuber", "target": "immersive media"}, {"source": "Benjamin Seide, Ross Williams & Elke Reinhuber", "target": "digital heritage representation"}, {"source": "Benjamin Seide, Ross Williams & Elke Reinhuber", "target": "glitch"}, {"source": "Benjamin Seide, Ross Williams & Elke Reinhuber", "target": "ambisonic"}, {"source": "Jason Kennedy", "target": "synthespian"}, {"source": "Jason Kennedy", "target": "digital double"}, {"source": "Jason Kennedy", "target": "acting"}, {"source": "Jason Kennedy", "target": "performance"}, {"source": "Jason Kennedy", "target": "animation"}, {"source": "Jason Kennedy", "target": "motion capture"}, {"source": "Jason Kennedy", "target": "vactor"}, {"source": "Pablo Gobira & Emanuelle de Oliveira Silva", "target": "art museum; virtual reality; immersion; digital arts; new media art"}, {"source": "Sieun Park, Suk Chon, Tiffany Lee & Jusub Kim", "target": "virtual reality"}, {"source": "Sieun Park, Suk Chon, Tiffany Lee & Jusub Kim", "target": "virtual exhibition"}, {"source": "Sieun Park, Suk Chon, Tiffany Lee & Jusub Kim", "target": "digital storytelling"}, {"source": "Sieun Park, Suk Chon, Tiffany Lee & Jusub Kim", "target": "new media"}, {"source": "Sieun Park, Suk Chon, Tiffany Lee & Jusub Kim", "target": "user experience"}, {"source": "Cynthia Patricia Villagomez Oviedo", "target": "electronic art"}, {"source": "Cynthia Patricia Villagomez Oviedo", "target": "processes"}, {"source": "Cynthia Patricia Villagomez Oviedo", "target": "creation"}, {"source": "Cynthia Patricia Villagomez Oviedo", "target": "reutilization"}, {"source": "Cynthia Patricia Villagomez Oviedo", "target": "reinterpretation"}, {"source": "Jens Herder, Shinpei Takeda, Kai Vermeegen, Till Davin, Dominique Berners, Bektur Ryskeldiev, Christian Zimmer, Ivana Druzetic & Christian Geiger", "target": "mixed reality"}, {"source": "Jens Herder, Shinpei Takeda, Kai Vermeegen, Till Davin, Dominique Berners, Bektur Ryskeldiev, Christian Zimmer, Ivana Druzetic & Christian Geiger", "target": "augmented reality"}, {"source": "Jens Herder, Shinpei Takeda, Kai Vermeegen, Till Davin, Dominique Berners, Bektur Ryskeldiev, Christian Zimmer, Ivana Druzetic & Christian Geiger", "target": "augmented virtuality"}, {"source": "Jens Herder, Shinpei Takeda, Kai Vermeegen, Till Davin, Dominique Berners, Bektur Ryskeldiev, Christian Zimmer, Ivana Druzetic & Christian Geiger", "target": "rapid prototyping"}, {"source": "Jens Herder, Shinpei Takeda, Kai Vermeegen, Till Davin, Dominique Berners, Bektur Ryskeldiev, Christian Zimmer, Ivana Druzetic & Christian Geiger", "target": "video conferencing"}, {"source": "Larissa Hjorth", "target": "mobile art"}, {"source": "Larissa Hjorth", "target": "visuality"}, {"source": "Larissa Hjorth", "target": "mobile media"}, {"source": "Larissa Hjorth", "target": "datafication"}, {"source": "Carly Whitaker", "target": "internet art"}, {"source": "Carly Whitaker", "target": "digital residency"}, {"source": "Carly Whitaker", "target": "networked curatorial practice"}, {"source": "Carly Whitaker", "target": "decolonization"}, {"source": "Carly Whitaker", "target": "global south"}, {"source": "Kiran Bhumber & Nancy Lee", "target": "vr performance"}, {"source": "Kiran Bhumber & Nancy Lee", "target": "virtual reality"}, {"source": "Kiran Bhumber & Nancy Lee", "target": "trumpet performance"}, {"source": "Kiran Bhumber & Nancy Lee", "target": "spatial music"}, {"source": "Lindsay D. Grace", "target": "digital narrative"}, {"source": "Lindsay D. Grace", "target": "recursion"}, {"source": "Lindsay D. Grace", "target": "level design"}, {"source": "Lindsay D. Grace", "target": "hauntology"}, {"source": "Lindsay D. Grace", "target": "critical design"}, {"source": "Jo\u00e3o Martinho Moura, N\u00e9 Barros & Paulo Ferreira-Lopes", "target": "digital performance"}, {"source": "Jo\u00e3o Martinho Moura, N\u00e9 Barros & Paulo Ferreira-Lopes", "target": "virtual reality"}, {"source": "Jo\u00e3o Martinho Moura, N\u00e9 Barros & Paulo Ferreira-Lopes", "target": "dance"}, {"source": "Jo\u00e3o Martinho Moura, N\u00e9 Barros & Paulo Ferreira-Lopes", "target": "embodiment"}, {"source": "Jo\u00e3o Martinho Moura, N\u00e9 Barros & Paulo Ferreira-Lopes", "target": "cyberspace"}, {"source": "Jo\u00e3o Martinho Moura, N\u00e9 Barros & Paulo Ferreira-Lopes", "target": "media arts"}, {"source": "Irene Eunyoung Lee", "target": "before the digital age"}, {"source": "Irene Eunyoung Lee", "target": "humans spent years in training to gain matured physical fidelity and versatility necessary to become professionals in music"}, {"source": "Irene Eunyoung Lee", "target": "which nowadays is often called the organization of sound. as the concept of sound art expands and becomes more diverse and inclusive of various practices and activities made possible through the technological advancements of our era"}, {"source": "Irene Eunyoung Lee", "target": "the organization of sound in artworks no longer necessarily requires time restrictions or physicality. we certainly don\u2019t know how expansively this \u201cbetween categories\u201d genre will develop yet. this essay presents the background thought process"}, {"source": "Irene Eunyoung Lee", "target": "through social and cultural perspectives"}, {"source": "Irene Eunyoung Lee", "target": "behind an in-progress sound art project to create a paean and elegy of human mortality through a self-driven artistic composition. the self-termed physimusiking practice led this artist to self-study a musical instrument and yoga movements. the journey of building new craftsmanship"}, {"source": "Irene Eunyoung Lee", "target": "by itself"}, {"source": "Irene Eunyoung Lee", "target": "is part of the experiment in unifying original auditory-visual expressions"}, {"source": "Irene Eunyoung Lee", "target": "somewhat similar to visual music. the multiple-year project was initiated in november of 2017 in hong kong with an announcement of the imprecise future schedule of three-tier"}, {"source": "Irene Eunyoung Lee", "target": "evolving stages leading to the final assembly in south korea."}, {"source": "Yanai Toister", "target": "history of photography; vision; speed of light; algorithmic speed; post-photography."}, {"source": "Scott Rettberg", "target": "cognitive assemblage"}, {"source": "Scott Rettberg", "target": "distributed cognition"}, {"source": "Scott Rettberg", "target": "ecological art"}, {"source": "Scott Rettberg", "target": "ecology"}, {"source": "Scott Rettberg", "target": "nature"}, {"source": "Scott Rettberg", "target": "cyber-semiotics"}, {"source": "Scott Rettberg", "target": "metaphor"}, {"source": "Scott Rettberg", "target": "installation"}, {"source": "Scott Rettberg", "target": "immersion"}, {"source": "Scott Rettberg", "target": "machine learning"}, {"source": "Yolande Harris", "target": "underwater sound"}, {"source": "Yolande Harris", "target": "sonic consciousness"}, {"source": "Yolande Harris", "target": "marine mammals"}, {"source": "Yolande Harris", "target": "sound walks"}, {"source": "Yolande Harris", "target": "listening"}, {"source": "Yolande Harris", "target": "deep listening"}, {"source": "Yolande Harris", "target": "environmental art"}, {"source": "Yolande Harris", "target": "embodied knowing."}, {"source": "Alejandro Rodriguez & Tomas Laurenzo", "target": "xr"}, {"source": "Alejandro Rodriguez & Tomas Laurenzo", "target": "mixed reality"}, {"source": "Alejandro Rodriguez & Tomas Laurenzo", "target": "surveillance"}, {"source": "Alejandro Rodriguez & Tomas Laurenzo", "target": "privacy"}, {"source": "Alejandro Rodriguez & Tomas Laurenzo", "target": "biometrics"}, {"source": "Alejandro Rodriguez & Tomas Laurenzo", "target": "altered reality"}, {"source": "Alejandro Rodriguez & Tomas Laurenzo", "target": "mediated reality"}, {"source": "Alejandro Rodriguez & Tomas Laurenzo", "target": "virtual reality."}, {"source": "Ellen Pearlman", "target": "emotionally intelligent artificial intelligence"}, {"source": "Ellen Pearlman", "target": "brain computer interfaces"}, {"source": "Ellen Pearlman", "target": "human computer interaction"}, {"source": "Ellen Pearlman", "target": "performance"}, {"source": "Chanjun Mu", "target": "intervals; interactive storytelling; interactive documentary"}, {"source": "Jing Han", "target": "new media art"}, {"source": "Jing Han", "target": "chinese oiled-paper umbrella"}, {"source": "Jing Han", "target": "traditional skills"}, {"source": "Jing Han", "target": "regeneration"}, {"source": "Tobias Klein & Harald Kraemer", "target": "algorithmic art"}, {"source": "Tobias Klein & Harald Kraemer", "target": "ornament"}, {"source": "Tobias Klein & Harald Kraemer", "target": "3d printing"}, {"source": "Tobias Klein & Harald Kraemer", "target": "rococo"}, {"source": "Tobias Klein & Harald Kraemer", "target": "symmetry"}, {"source": "Tobias Klein & Harald Kraemer", "target": "asymmetry"}, {"source": "Tobias Klein & Harald Kraemer", "target": "landscape"}, {"source": "Tobias Klein & Harald Kraemer", "target": "wunderkammer"}, {"source": "Janna Ahrndt", "target": "feminism"}, {"source": "Janna Ahrndt", "target": "craft"}, {"source": "Janna Ahrndt", "target": "wearable technology"}, {"source": "Janna Ahrndt", "target": "workshop"}, {"source": "Janna Ahrndt", "target": "activism"}, {"source": "Janna Ahrndt", "target": "social media"}, {"source": "Janna Ahrndt", "target": "accountability"}, {"source": "Janna Ahrndt", "target": "community"}, {"source": "Janna Ahrndt", "target": "ethics"}, {"source": "Janna Ahrndt", "target": "environmentalism"}, {"source": "Masayuki Akamatsu, Yasuko Imura, Tomoki Kobayashi, Iku Harada & Shigeru Matsui", "target": "ar"}, {"source": "Masayuki Akamatsu, Yasuko Imura, Tomoki Kobayashi, Iku Harada & Shigeru Matsui", "target": "rtk-gnss"}, {"source": "Masayuki Akamatsu, Yasuko Imura, Tomoki Kobayashi, Iku Harada & Shigeru Matsui", "target": "hsr"}, {"source": "Masayuki Akamatsu, Yasuko Imura, Tomoki Kobayashi, Iku Harada & Shigeru Matsui", "target": "drone"}, {"source": "Masayuki Akamatsu, Yasuko Imura, Tomoki Kobayashi, Iku Harada & Shigeru Matsui", "target": "computational imaging"}, {"source": "Masayuki Akamatsu, Yasuko Imura, Tomoki Kobayashi, Iku Harada & Shigeru Matsui", "target": "imaginary modeling"}, {"source": "Masayuki Akamatsu, Yasuko Imura, Tomoki Kobayashi, Iku Harada & Shigeru Matsui", "target": "audience theory"}, {"source": "Masayuki Akamatsu, Yasuko Imura, Tomoki Kobayashi, Iku Harada & Shigeru Matsui", "target": "archives of media art"}, {"source": "Sara Bonaventura", "target": "experimental"}, {"source": "Sara Bonaventura", "target": "video installation"}, {"source": "Sara Bonaventura", "target": "videodance"}, {"source": "Sara Bonaventura", "target": "performing arts"}, {"source": "Sara Bonaventura", "target": "choreography"}, {"source": "Sara Bonaventura", "target": "analog"}, {"source": "Sara Bonaventura", "target": "video synthesizers"}, {"source": "Sara Bonaventura", "target": "wobbu-lator"}, {"source": "Sara Bonaventura", "target": "raster manipulation unit"}, {"source": "Sara Bonaventura", "target": "nam june paik"}, {"source": "Reynaldo Thompson & Tirtha Prasad Mukhopadhyay", "target": "prespacetime"}, {"source": "Reynaldo Thompson & Tirtha Prasad Mukhopadhyay", "target": "schumann resonance"}, {"source": "Reynaldo Thompson & Tirtha Prasad Mukhopadhyay", "target": "stroboscopic light"}, {"source": "Reynaldo Thompson & Tirtha Prasad Mukhopadhyay", "target": "water"}, {"source": "Ha Na Lee & James Hughes", "target": "public art"}, {"source": "Ha Na Lee & James Hughes", "target": "virtual reality"}, {"source": "Ha Na Lee & James Hughes", "target": "360 video"}, {"source": "Ha Na Lee & James Hughes", "target": "computer vision"}, {"source": "Ha Na Lee & James Hughes", "target": "socially engaged art"}, {"source": "Marios Samdanis, Chrystalla Kapetaniou, Yi Kyung Kim & Soo Hee Lee", "target": "remediation"}, {"source": "Marios Samdanis, Chrystalla Kapetaniou, Yi Kyung Kim & Soo Hee Lee", "target": "digital art"}, {"source": "Marios Samdanis, Chrystalla Kapetaniou, Yi Kyung Kim & Soo Hee Lee", "target": "digital design"}, {"source": "Marios Samdanis, Chrystalla Kapetaniou, Yi Kyung Kim & Soo Hee Lee", "target": "interactivity"}, {"source": "Yan Breuleux & R\u00e9mi Lapierre", "target": "sound and music computing"}, {"source": "Yan Breuleux & R\u00e9mi Lapierre", "target": "live performance"}, {"source": "Yan Breuleux & R\u00e9mi Lapierre", "target": "colour organ"}, {"source": "Yan Breuleux & R\u00e9mi Lapierre", "target": "virtual colour organ (vco)"}, {"source": "Yan Breuleux & R\u00e9mi Lapierre", "target": "visual music"}, {"source": "Yan Breuleux & R\u00e9mi Lapierre", "target": "fulldome"}, {"source": "Yan Breuleux & R\u00e9mi Lapierre", "target": "environmental storytelling"}, {"source": "Yan Breuleux & R\u00e9mi Lapierre", "target": "immersive media"}, {"source": "Yan Breuleux & R\u00e9mi Lapierre", "target": "virtual reality."}, {"source": "Sabina Hyoju Ahn", "target": "microbial data transformation"}, {"source": "Sabina Hyoju Ahn", "target": "bco"}, {"source": "Sabina Hyoju Ahn", "target": "sonification"}, {"source": "Sabina Hyoju Ahn", "target": "biobattery"}, {"source": "Sabina Hyoju Ahn", "target": "bioelectricity"}, {"source": "Sabina Hyoju Ahn", "target": "control voltage"}, {"source": "Sabina Hyoju Ahn", "target": "microcosm"}, {"source": "Sabina Hyoju Ahn", "target": "winogradsky column"}, {"source": "Sabina Hyoju Ahn", "target": "energy harvesting"}, {"source": "Sabina Hyoju Ahn", "target": "dark fermentation"}, {"source": "Haoyi Zhang", "target": "movable type printing"}, {"source": "Haoyi Zhang", "target": "digital media art"}, {"source": "Haoyi Zhang", "target": "thinking "}, {"source": "Paul Sermon", "target": "telematic"}, {"source": "Paul Sermon", "target": "installation"}, {"source": "Paul Sermon", "target": "telepresence"}, {"source": "Paul Sermon", "target": "proprioceptive"}, {"source": "Paul Sermon", "target": "chat"}, {"source": "Paul Sermon", "target": "interface"}, {"source": "Paul Sermon", "target": "keyboard"}, {"source": "Paul Sermon", "target": "cognitive"}, {"source": "Paul Sermon", "target": "illusion"}, {"source": "Paul Sermon", "target": "intimacy"}, {"source": "Jooyoung Oh & Byungjoo Lee", "target": "selfie"}, {"source": "Jooyoung Oh & Byungjoo Lee", "target": "interactive art installation"}, {"source": "Jooyoung Oh & Byungjoo Lee", "target": "sns"}, {"source": "Andrew R. Brown, John Ferguson & Andy Bennett", "target": "sharing"}, {"source": "Andrew R. Brown, John Ferguson & Andy Bennett", "target": "tools"}, {"source": "Andrew R. Brown, John Ferguson & Andy Bennett", "target": "production"}, {"source": "Andrew R. Brown, John Ferguson & Andy Bennett", "target": "music"}, {"source": "Andrew R. Brown, John Ferguson & Andy Bennett", "target": "media"}, {"source": "Andrew R. Brown, John Ferguson & Andy Bennett", "target": "collaboration"}, {"source": "Andrew R. Brown, John Ferguson & Andy Bennett", "target": "electronic"}, {"source": "Andrew R. Brown, John Ferguson & Andy Bennett", "target": "online"}, {"source": "Andrew R. Brown, John Ferguson & Andy Bennett", "target": "open."}, {"source": "Kazuhiro Jo, Ryota Kuwakubo, Akira Segawa, Takuro Oshima, Yusuke Gushiken, Asami Takami & johnsmith", "target": "personal fabrication"}, {"source": "Kazuhiro Jo, Ryota Kuwakubo, Akira Segawa, Takuro Oshima, Yusuke Gushiken, Asami Takami & johnsmith", "target": "media archaeology"}, {"source": "Kazuhiro Jo, Ryota Kuwakubo, Akira Segawa, Takuro Oshima, Yusuke Gushiken, Asami Takami & johnsmith", "target": "acoustics"}, {"source": "Kazuhiro Jo, Ryota Kuwakubo, Akira Segawa, Takuro Oshima, Yusuke Gushiken, Asami Takami & johnsmith", "target": "graphics"}, {"source": "Kazuhiro Jo, Ryota Kuwakubo, Akira Segawa, Takuro Oshima, Yusuke Gushiken, Asami Takami & johnsmith", "target": "optics"}, {"source": "Taekyeom Lee", "target": "education"}, {"source": "Taekyeom Lee", "target": "digital"}, {"source": "Taekyeom Lee", "target": "technology"}, {"source": "Taekyeom Lee", "target": "interdisciplinary"}, {"source": "Taekyeom Lee", "target": "typography"}, {"source": "Taekyeom Lee", "target": "dimensional typography"}, {"source": "Taekyeom Lee", "target": "digital fabrication"}, {"source": "Taekyeom Lee", "target": "cad"}, {"source": "Taekyeom Lee", "target": "3-d printing"}, {"source": "Taekyeom Lee", "target": "cnc milling"}, {"source": "Taekyeom Lee", "target": "material study"}, {"source": "Taekyeom Lee", "target": "graphic design"}, {"source": "Taekyeom Lee", "target": "post-digital"}, {"source": "Taekyeom Lee", "target": "analog and digital."}, {"source": "V\u00edt Ru\u017eicka, Eunsu Kang, David Gordon, Ankita Patel, Jacqui Fashimpaur & Manzil Zaheer", "target": "fake news"}, {"source": "V\u00edt Ru\u017eicka, Eunsu Kang, David Gordon, Ankita Patel, Jacqui Fashimpaur & Manzil Zaheer", "target": "article generation"}, {"source": "V\u00edt Ru\u017eicka, Eunsu Kang, David Gordon, Ankita Patel, Jacqui Fashimpaur & Manzil Zaheer", "target": "lstm"}, {"source": "V\u00edt Ru\u017eicka, Eunsu Kang, David Gordon, Ankita Patel, Jacqui Fashimpaur & Manzil Zaheer", "target": "rnn"}, {"source": "V\u00edt Ru\u017eicka, Eunsu Kang, David Gordon, Ankita Patel, Jacqui Fashimpaur & Manzil Zaheer", "target": "language model"}, {"source": "V\u00edt Ru\u017eicka, Eunsu Kang, David Gordon, Ankita Patel, Jacqui Fashimpaur & Manzil Zaheer", "target": "machine learning"}, {"source": "V\u00edt Ru\u017eicka, Eunsu Kang, David Gordon, Ankita Patel, Jacqui Fashimpaur & Manzil Zaheer", "target": "ai"}, {"source": "V\u00edt Ru\u017eicka, Eunsu Kang, David Gordon, Ankita Patel, Jacqui Fashimpaur & Manzil Zaheer", "target": "media art"}, {"source": "V\u00edt Ru\u017eicka, Eunsu Kang, David Gordon, Ankita Patel, Jacqui Fashimpaur & Manzil Zaheer", "target": "internet art"}, {"source": "V\u00edt Ru\u017eicka, Eunsu Kang, David Gordon, Ankita Patel, Jacqui Fashimpaur & Manzil Zaheer", "target": "web"}, {"source": "V\u00edt Ru\u017eicka, Eunsu Kang, David Gordon, Ankita Patel, Jacqui Fashimpaur & Manzil Zaheer", "target": "blog"}, {"source": "V\u00edt Ru\u017eicka, Eunsu Kang, David Gordon, Ankita Patel, Jacqui Fashimpaur & Manzil Zaheer", "target": "human-ai co-creation"}, {"source": "David Han", "target": "virtual reality"}, {"source": "David Han", "target": "media archaeology"}, {"source": "David Han", "target": "closed-circuit video installation art"}, {"source": "David Han", "target": "media art"}, {"source": "David Han", "target": "dan graham"}, {"source": "Anna Madeleine Raupach", "target": "augmented reality"}, {"source": "Anna Madeleine Raupach", "target": "media art"}, {"source": "Anna Madeleine Raupach", "target": "animation"}, {"source": "Anna Madeleine Raupach", "target": "climate change"}, {"source": "Anna Madeleine Raupach", "target": "temporality"}, {"source": "Anna Madeleine Raupach", "target": "installation art"}, {"source": "Anna Madeleine Raupach", "target": "site-specific art"}, {"source": "Anna Madeleine Raupach", "target": "moving image"}, {"source": "Anna Madeleine Raupach", "target": "hypernatural."}, {"source": "Honghao Deng, Jiabao Li, Xuesong Zhang & Panagiotis Michalatos", "target": "interactive architecture"}, {"source": "Honghao Deng, Jiabao Li, Xuesong Zhang & Panagiotis Michalatos", "target": "microclimate"}, {"source": "Honghao Deng, Jiabao Li, Xuesong Zhang & Panagiotis Michalatos", "target": "architectural spaces"}, {"source": "Honghao Deng, Jiabao Li, Xuesong Zhang & Panagiotis Michalatos", "target": "vapor geometry"}, {"source": "Honghao Deng, Jiabao Li, Xuesong Zhang & Panagiotis Michalatos", "target": "humidity control"}, {"source": "Honghao Deng, Jiabao Li, Xuesong Zhang & Panagiotis Michalatos", "target": "responsive environment"}, {"source": "Jin Woo Lee, Yikyung Kim & Soo Hee Lee", "target": "human-computer interaction"}, {"source": "Jin Woo Lee, Yikyung Kim & Soo Hee Lee", "target": "remediation"}, {"source": "Jin Woo Lee, Yikyung Kim & Soo Hee Lee", "target": "user experience"}, {"source": "Jin Woo Lee, Yikyung Kim & Soo Hee Lee", "target": "digital museum"}, {"source": "Jin Woo Lee, Yikyung Kim & Soo Hee Lee", "target": "google art & culture"}, {"source": "John Power", "target": "ambient commons"}, {"source": "John Power", "target": "generative art"}, {"source": "John Power", "target": "calm technology"}, {"source": "John Power", "target": "public space"}, {"source": "John Power", "target": "place making"}, {"source": "Aur\u00e9lie Besson", "target": "embodiment"}, {"source": "Aur\u00e9lie Besson", "target": "embodied cognition"}, {"source": "Aur\u00e9lie Besson", "target": "interactive art"}, {"source": "Aur\u00e9lie Besson", "target": "aesthetics"}, {"source": "Aur\u00e9lie Besson", "target": "experience"}, {"source": "Aur\u00e9lie Besson", "target": "movement senses"}, {"source": "Young Ho Kim, Yang Kyu Lim & Jin Wan Park", "target": "npr"}, {"source": "Young Ho Kim, Yang Kyu Lim & Jin Wan Park", "target": "media"}, {"source": "Young Ho Kim, Yang Kyu Lim & Jin Wan Park", "target": "illustration"}, {"source": "Young Ho Kim, Yang Kyu Lim & Jin Wan Park", "target": "art"}, {"source": "Sadia Sadia", "target": "transcendence"}, {"source": "Sadia Sadia", "target": "catharsis"}, {"source": "Sadia Sadia", "target": "epiphany"}, {"source": "Sadia Sadia", "target": "encompassing"}, {"source": "Sadia Sadia", "target": "installation"}, {"source": "Sadia Sadia", "target": "spatial"}, {"source": "Sadia Sadia", "target": "universality"}, {"source": "Sadia Sadia", "target": "communion"}, {"source": "Sadia Sadia", "target": "perception"}, {"source": "Sadia Sadia", "target": "consciousness"}, {"source": "Andrew Richardson", "target": "data"}, {"source": "Andrew Richardson", "target": "visualization"}, {"source": "Andrew Richardson", "target": "light"}, {"source": "Andrew Richardson", "target": "location"}, {"source": "Andrew Richardson", "target": "city"}, {"source": "Andrew Richardson", "target": "graphics"}, {"source": "Andrew Richardson", "target": "impressionism."}, {"source": "Anastasia Tyurina", "target": "scanning electron microscope"}, {"source": "Anastasia Tyurina", "target": "signal processing"}, {"source": "Anastasia Tyurina", "target": "image processing"}, {"source": "Anastasia Tyurina", "target": "photomicrography"}, {"source": "Anastasia Tyurina", "target": "photography."}, {"source": "Mengyu Chen, Jing Yan & Yin Yu", "target": "data visceralization"}, {"source": "Mengyu Chen, Jing Yan & Yin Yu", "target": "soft robotics"}, {"source": "Mengyu Chen, Jing Yan & Yin Yu", "target": "haptics"}, {"source": "Mengyu Chen, Jing Yan & Yin Yu", "target": "virtual reality"}, {"source": "Mengyu Chen, Jing Yan & Yin Yu", "target": "affective computing"}, {"source": "Mengyu Chen, Jing Yan & Yin Yu", "target": "biometrics"}, {"source": "David Behar", "target": "natural light"}, {"source": "David Behar", "target": "responsive environment"}, {"source": "David Behar", "target": "space interaction"}, {"source": "David Behar", "target": "penumbra"}, {"source": "David Behar", "target": "camera obscura"}, {"source": "David Behar", "target": "phenomenology."}, {"source": "Stahl Stenslie", "target": "somatic art"}, {"source": "Stahl Stenslie", "target": "immersive art"}, {"source": "Stahl Stenslie", "target": "lethal interaction"}, {"source": "Stahl Stenslie", "target": "interactive installations."}, {"source": "Helena Ferreira", "target": "projection"}, {"source": "Helena Ferreira", "target": "introjection"}, {"source": "Helena Ferreira", "target": "light"}, {"source": "Helena Ferreira", "target": "shadows"}, {"source": "Helena Ferreira", "target": "materiality"}, {"source": "Helena Ferreira", "target": "landscape."}, {"source": "Paula Andrea Escand\u00f3n, Andr\u00e9s Felipe Rold\u00e1n & Fernando Luna", "target": "architecture"}, {"source": "Paula Andrea Escand\u00f3n, Andr\u00e9s Felipe Rold\u00e1n & Fernando Luna", "target": "space"}, {"source": "Paula Andrea Escand\u00f3n, Andr\u00e9s Felipe Rold\u00e1n & Fernando Luna", "target": "composition"}, {"source": "Paula Andrea Escand\u00f3n, Andr\u00e9s Felipe Rold\u00e1n & Fernando Luna", "target": "light and shadow"}, {"source": "Paula Andrea Escand\u00f3n, Andr\u00e9s Felipe Rold\u00e1n & Fernando Luna", "target": "perception"}, {"source": "Paula Andrea Escand\u00f3n, Andr\u00e9s Felipe Rold\u00e1n & Fernando Luna", "target": "installation."}, {"source": "Clarissa Ribeiro", "target": "molmedia (neologism)"}, {"source": "Clarissa Ribeiro", "target": "personality transplants"}, {"source": "Clarissa Ribeiro", "target": "microbiome anthropophagy"}, {"source": "Clarissa Ribeiro", "target": "neuroregenerative nutrition. microbial resource management"}, {"source": "Clarissa Ribeiro", "target": "cannibalist manifesto"}, {"source": "Clarissa Ribeiro", "target": "psychobiotics"}, {"source": "Clarissa Ribeiro", "target": "art and science"}, {"source": "Clarissa Ribeiro", "target": "relational food"}, {"source": "Clarissa Ribeiro", "target": "probiotics"}, {"source": "Joel Ong", "target": "wind"}, {"source": "Joel Ong", "target": "data visualization"}, {"source": "Joel Ong", "target": "elemental media"}, {"source": "Joel Ong", "target": "migration"}, {"source": "Nima Navab & Desiree Foerster", "target": "process philosophy"}, {"source": "Nima Navab & Desiree Foerster", "target": "embodied cognition"}, {"source": "Nima Navab & Desiree Foerster", "target": "enactivism"}, {"source": "Nima Navab & Desiree Foerster", "target": "rhythmanalysis"}, {"source": "Nima Navab & Desiree Foerster", "target": "responsive media ecologies"}, {"source": "Nima Navab & Desiree Foerster", "target": "ambient environmental feedback"}, {"source": "Nima Navab & Desiree Foerster", "target": "material computation"}, {"source": "Nima Navab & Desiree Foerster", "target": "fluid dynamics"}, {"source": "Nima Navab & Desiree Foerster", "target": "caustics"}, {"source": "Nima Navab & Desiree Foerster", "target": "dissipative structures."}, {"source": "Nadja Lipsyc", "target": "game design"}, {"source": "Nadja Lipsyc", "target": "immersion"}, {"source": "Nadja Lipsyc", "target": "vr"}, {"source": "Nadja Lipsyc", "target": "roleplaying"}, {"source": "Nadja Lipsyc", "target": "environmental design"}, {"source": "Nadja Lipsyc", "target": "art-research"}, {"source": "Nadja Lipsyc", "target": "360 storytelling"}, {"source": "Nadja Lipsyc", "target": "larp"}, {"source": "Nadja Lipsyc", "target": "world building"}, {"source": "Nadja Lipsyc", "target": "agile methods"}, {"source": "Nadja Lipsyc", "target": "character"}, {"source": "Meredith Drum", "target": "animation"}, {"source": "Meredith Drum", "target": "avatars"}, {"source": "Meredith Drum", "target": "cultural studies"}, {"source": "Meredith Drum", "target": "digital bodies"}, {"source": "Meredith Drum", "target": "feminism"}, {"source": "Meredith Drum", "target": "game studies"}, {"source": "Meredith Drum", "target": "gender"}, {"source": "Meredith Drum", "target": "media representation"}, {"source": "Meredith Drum", "target": "scopic regime"}, {"source": "Meredith Drum", "target": "virtual humans"}, {"source": "Francisco Gerardo Toledo Ram\u00edrez", "target": "liminality"}, {"source": "Francisco Gerardo Toledo Ram\u00edrez", "target": "autoempathy"}, {"source": "Francisco Gerardo Toledo Ram\u00edrez", "target": "machinic-subjectivity"}, {"source": "Francisco Gerardo Toledo Ram\u00edrez", "target": "dualsubjectivity"}, {"source": "Francisco Gerardo Toledo Ram\u00edrez", "target": "myth-making"}, {"source": "Francisco Gerardo Toledo Ram\u00edrez", "target": "identity-flow"}, {"source": "Francisco Gerardo Toledo Ram\u00edrez", "target": "avatar interaction."}, {"source": "Raivo Kelomees", "target": "interactive art"}, {"source": "Raivo Kelomees", "target": "digital art"}, {"source": "Raivo Kelomees", "target": "spectator paradigm"}, {"source": "Raivo Kelomees", "target": "gaze of the artwork"}, {"source": "Raivo Kelomees", "target": "symbiotic interaction"}, {"source": "Raivo Kelomees", "target": "biofeedback art"}, {"source": "Raivo Kelomees", "target": "machine vision"}, {"source": "Raivo Kelomees", "target": "surveillance art"}, {"source": "Raivo Kelomees", "target": "viewer-sensing artworks."}, {"source": "Lindsay D. Grace", "target": "recursive design"}, {"source": "Lindsay D. Grace", "target": "game design"}, {"source": "Lindsay D. Grace", "target": "social impact games"}, {"source": "Lindsay D. Grace", "target": "meaningful play"}, {"source": "Eun Sun Chu, Jacqueline Gonzalez, Jinsil Hwaryoung Seo & Caleb Kicklighter", "target": "360 video"}, {"source": "Eun Sun Chu, Jacqueline Gonzalez, Jinsil Hwaryoung Seo & Caleb Kicklighter", "target": "immersive experience"}, {"source": "Eun Sun Chu, Jacqueline Gonzalez, Jinsil Hwaryoung Seo & Caleb Kicklighter", "target": "narrative"}, {"source": "Eun Sun Chu, Jacqueline Gonzalez, Jinsil Hwaryoung Seo & Caleb Kicklighter", "target": "color blindness"}, {"source": "Eun Sun Chu, Jacqueline Gonzalez, Jinsil Hwaryoung Seo & Caleb Kicklighter", "target": "awareness"}, {"source": "James Shea", "target": "hong kong"}, {"source": "James Shea", "target": "yellow umbrella"}, {"source": "James Shea", "target": "videogame"}, {"source": "James Shea", "target": "play"}, {"source": "James Shea", "target": "politics"}, {"source": "James Shea", "target": "copyright"}, {"source": "James Shea", "target": "censorship"}, {"source": "James Shea", "target": "d\u00e9tournement"}, {"source": "James Shea", "target": "\u201csecondary creation\u201d"}, {"source": "Mariana P\u00e9rez-Bobadilla", "target": "microbiopolitics"}, {"source": "Mariana P\u00e9rez-Bobadilla", "target": "art and biology"}, {"source": "Mariana P\u00e9rez-Bobadilla", "target": "posthuman"}, {"source": "Mariana P\u00e9rez-Bobadilla", "target": "bioart"}, {"source": "Mariana P\u00e9rez-Bobadilla", "target": "bacteria"}, {"source": "Mariana P\u00e9rez-Bobadilla", "target": "new materialism"}, {"source": "Tomas Laurenzo", "target": "interaction"}, {"source": "Tomas Laurenzo", "target": "blinking"}, {"source": "Tomas Laurenzo", "target": "surveillance"}, {"source": "Tomas Laurenzo", "target": "computer vision."}, {"source": "Gyung Jin Shin", "target": "participatory art"}, {"source": "Gyung Jin Shin", "target": "social networking service"}, {"source": "Gyung Jin Shin", "target": "social media"}, {"source": "Gyung Jin Shin", "target": "web 2.0"}, {"source": "Gyung Jin Shin", "target": "candlelight protest"}, {"source": "Gyung Jin Shin", "target": "participation"}, {"source": "Gyung Jin Shin", "target": "authorship"}, {"source": "Gyung Jin Shin", "target": "spectatorship"}, {"source": "Gyung Jin Shin", "target": "patronship"}, {"source": "Kyungho Lee", "target": "misplaced euphoria is an interactive performance that consists of expressive movement"}, {"source": "Kyungho Lee", "target": "expressive gesture recognition"}, {"source": "Kyungho Lee", "target": "and interactive visualization that aims to develop empathy for people with bipolar disorder. this project explored the characteristics of those with bipolar disorder through the mediums of dance and interactive visualization driven by expressive gesture recognition. to develop an interactive performance"}, {"source": "Kyungho Lee", "target": "we conducted an interview with a person to gather information. we used the insights collected from the interview processes as a base for our creative process. to convey the inner state of the dancer to the audience"}, {"source": "Kyungho Lee", "target": "6-dof acceleration sensors"}, {"source": "Kyungho Lee", "target": "attached to the dancers arms"}, {"source": "Kyungho Lee", "target": "were used to capture her movement. we then used the support vector machine (svm) to parameterize the dancers expression"}, {"source": "Kyungho Lee", "target": "and the results were visualized through the rutt-etra algorithm on a real-time basis."}, {"source": "Sung-A Jang & Benjamin L\u2019Huillier", "target": "immersive data visualization"}, {"source": "Sung-A Jang & Benjamin L\u2019Huillier", "target": "virtual reality"}, {"source": "Sung-A Jang & Benjamin L\u2019Huillier", "target": "korean constellations"}, {"source": "Sung-A Jang & Benjamin L\u2019Huillier", "target": "star maps"}, {"source": "Sung-A Jang & Benjamin L\u2019Huillier", "target": "astronomy"}]